apple_maps/__init__.py
apple_maps/client.py
apple_maps-0.1.0.dist-info/LICENSE
apple_maps-0.1.0.dist-info/METADATA
apple_maps-0.1.0.dist-info/WHEEL
apple_maps-0.1.0.dist-info/RECORD
